{"nodes": [{"id": "c_users_rshiv_nse_trading_bot_backend_utils_capital_filter_py", "label": "capital_filter.py", "file_type": "code", "source_file": "C:\\Users\\rshiv\\nse-trading-bot\\backend\\utils\\capital_filter.py", "source_location": "L1"}, {"id": "utils_capital_filter_calculate_trade_viability", "label": "calculate_trade_viability()", "file_type": "code", "source_file": "C:\\Users\\rshiv\\nse-trading-bot\\backend\\utils\\capital_filter.py", "source_location": "L19"}, {"id": "utils_capital_filter_filter_stocks_by_capital", "label": "filter_stocks_by_capital()", "file_type": "code", "source_file": "C:\\Users\\rshiv\\nse-trading-bot\\backend\\utils\\capital_filter.py", "source_location": "L87"}, {"id": "utils_capital_filter_rationale_1", "label": "Pre-filters the watchlist by capital before any expensive historical API calls.", "file_type": "rationale", "source_file": "C:\\Users\\rshiv\\nse-trading-bot\\backend\\utils\\capital_filter.py", "source_location": "L1"}, {"id": "utils_capital_filter_rationale_24", "label": "Check if trading this stock can realistically profit after all charges.      Ang", "file_type": "rationale", "source_file": "C:\\Users\\rshiv\\nse-trading-bot\\backend\\utils\\capital_filter.py", "source_location": "L24"}, {"id": "utils_capital_filter_rationale_93", "label": "Filter watchlist to only stocks that are affordable AND profitable to trade.", "file_type": "rationale", "source_file": "C:\\Users\\rshiv\\nse-trading-bot\\backend\\utils\\capital_filter.py", "source_location": "L93"}], "edges": [{"source": "c_users_rshiv_nse_trading_bot_backend_utils_capital_filter_py", "target": "logging", "relation": "imports", "confidence": "EXTRACTED", "source_file": "C:\\Users\\rshiv\\nse-trading-bot\\backend\\utils\\capital_filter.py", "source_location": "L13", "weight": 1.0}, {"source": "c_users_rshiv_nse_trading_bot_backend_utils_capital_filter_py", "target": "time", "relation": "imports", "confidence": "EXTRACTED", "source_file": "C:\\Users\\rshiv\\nse-trading-bot\\backend\\utils\\capital_filter.py", "source_location": "L14", "weight": 1.0}, {"source": "c_users_rshiv_nse_trading_bot_backend_utils_capital_filter_py", "target": "utils_capital_filter_calculate_trade_viability", "relation": "contains", "confidence": "EXTRACTED", "source_file": "C:\\Users\\rshiv\\nse-trading-bot\\backend\\utils\\capital_filter.py", "source_location": "L19", "weight": 1.0}, {"source": "c_users_rshiv_nse_trading_bot_backend_utils_capital_filter_py", "target": "utils_capital_filter_filter_stocks_by_capital", "relation": "contains", "confidence": "EXTRACTED", "source_file": "C:\\Users\\rshiv\\nse-trading-bot\\backend\\utils\\capital_filter.py", "source_location": "L87", "weight": 1.0}, {"source": "utils_capital_filter_filter_stocks_by_capital", "target": "utils_capital_filter_calculate_trade_viability", "relation": "calls", "confidence": "EXTRACTED", "source_file": "C:\\Users\\rshiv\\nse-trading-bot\\backend\\utils\\capital_filter.py", "source_location": "L131", "weight": 1.0}, {"source": "utils_capital_filter_rationale_1", "target": "c_users_rshiv_nse_trading_bot_backend_utils_capital_filter_py", "relation": "rationale_for", "confidence": "EXTRACTED", "source_file": "C:\\Users\\rshiv\\nse-trading-bot\\backend\\utils\\capital_filter.py", "source_location": "L1", "weight": 1.0}, {"source": "utils_capital_filter_rationale_24", "target": "utils_capital_filter_calculate_trade_viability", "relation": "rationale_for", "confidence": "EXTRACTED", "source_file": "C:\\Users\\rshiv\\nse-trading-bot\\backend\\utils\\capital_filter.py", "source_location": "L24", "weight": 1.0}, {"source": "utils_capital_filter_rationale_93", "target": "utils_capital_filter_filter_stocks_by_capital", "relation": "rationale_for", "confidence": "EXTRACTED", "source_file": "C:\\Users\\rshiv\\nse-trading-bot\\backend\\utils\\capital_filter.py", "source_location": "L93", "weight": 1.0}], "raw_calls": [{"caller_nid": "utils_capital_filter_calculate_trade_viability", "callee": "int", "source_file": "C:\\Users\\rshiv\\nse-trading-bot\\backend\\utils\\capital_filter.py", "source_location": "L50"}, {"caller_nid": "utils_capital_filter_calculate_trade_viability", "callee": "max", "source_file": "C:\\Users\\rshiv\\nse-trading-bot\\backend\\utils\\capital_filter.py", "source_location": "L57"}, {"caller_nid": "utils_capital_filter_calculate_trade_viability", "callee": "min", "source_file": "C:\\Users\\rshiv\\nse-trading-bot\\backend\\utils\\capital_filter.py", "source_location": "L57"}, {"caller_nid": "utils_capital_filter_calculate_trade_viability", "callee": "round", "source_file": "C:\\Users\\rshiv\\nse-trading-bot\\backend\\utils\\capital_filter.py", "source_location": "L74"}, {"caller_nid": "utils_capital_filter_calculate_trade_viability", "callee": "round", "source_file": "C:\\Users\\rshiv\\nse-trading-bot\\backend\\utils\\capital_filter.py", "source_location": "L75"}, {"caller_nid": "utils_capital_filter_calculate_trade_viability", "callee": "round", "source_file": "C:\\Users\\rshiv\\nse-trading-bot\\backend\\utils\\capital_filter.py", "source_location": "L76"}, {"caller_nid": "utils_capital_filter_calculate_trade_viability", "callee": "round", "source_file": "C:\\Users\\rshiv\\nse-trading-bot\\backend\\utils\\capital_filter.py", "source_location": "L77"}, {"caller_nid": "utils_capital_filter_filter_stocks_by_capital", "callee": "info", "source_file": "C:\\Users\\rshiv\\nse-trading-bot\\backend\\utils\\capital_filter.py", "source_location": "L113"}, {"caller_nid": "utils_capital_filter_filter_stocks_by_capital", "callee": "len", "source_file": "C:\\Users\\rshiv\\nse-trading-bot\\backend\\utils\\capital_filter.py", "source_location": "L113"}, {"caller_nid": "utils_capital_filter_filter_stocks_by_capital", "callee": "enumerate", "source_file": "C:\\Users\\rshiv\\nse-trading-bot\\backend\\utils\\capital_filter.py", "source_location": "L115"}, {"caller_nid": "utils_capital_filter_filter_stocks_by_capital", "callee": "get", "source_file": "C:\\Users\\rshiv\\nse-trading-bot\\backend\\utils\\capital_filter.py", "source_location": "L116"}, {"caller_nid": "utils_capital_filter_filter_stocks_by_capital", "callee": "get", "source_file": "C:\\Users\\rshiv\\nse-trading-bot\\backend\\utils\\capital_filter.py", "source_location": "L117"}, {"caller_nid": "utils_capital_filter_filter_stocks_by_capital", "callee": "wait", "source_file": "C:\\Users\\rshiv\\nse-trading-bot\\backend\\utils\\capital_filter.py", "source_location": "L120"}, {"caller_nid": "utils_capital_filter_filter_stocks_by_capital", "callee": "getMarketData", "source_file": "C:\\Users\\rshiv\\nse-trading-bot\\backend\\utils\\capital_filter.py", "source_location": "L122"}, {"caller_nid": "utils_capital_filter_filter_stocks_by_capital", "callee": "str", "source_file": "C:\\Users\\rshiv\\nse-trading-bot\\backend\\utils\\capital_filter.py", "source_location": "L124"}, {"caller_nid": "utils_capital_filter_filter_stocks_by_capital", "callee": "get", "source_file": "C:\\Users\\rshiv\\nse-trading-bot\\backend\\utils\\capital_filter.py", "source_location": "L127"}, {"caller_nid": "utils_capital_filter_filter_stocks_by_capital", "callee": "get", "source_file": "C:\\Users\\rshiv\\nse-trading-bot\\backend\\utils\\capital_filter.py", "source_location": "L127"}, {"caller_nid": "utils_capital_filter_filter_stocks_by_capital", "callee": "get", "source_file": "C:\\Users\\rshiv\\nse-trading-bot\\backend\\utils\\capital_filter.py", "source_location": "L127"}, {"caller_nid": "utils_capital_filter_filter_stocks_by_capital", "callee": "float", "source_file": "C:\\Users\\rshiv\\nse-trading-bot\\backend\\utils\\capital_filter.py", "source_location": "L128"}, {"caller_nid": "utils_capital_filter_filter_stocks_by_capital", "callee": "append", "source_file": "C:\\Users\\rshiv\\nse-trading-bot\\backend\\utils\\capital_filter.py", "source_location": "L136"}, {"caller_nid": "utils_capital_filter_filter_stocks_by_capital", "callee": "append", "source_file": "C:\\Users\\rshiv\\nse-trading-bot\\backend\\utils\\capital_filter.py", "source_location": "L138"}, {"caller_nid": "utils_capital_filter_filter_stocks_by_capital", "callee": "warning", "source_file": "C:\\Users\\rshiv\\nse-trading-bot\\backend\\utils\\capital_filter.py", "source_location": "L141"}, {"caller_nid": "utils_capital_filter_filter_stocks_by_capital", "callee": "append", "source_file": "C:\\Users\\rshiv\\nse-trading-bot\\backend\\utils\\capital_filter.py", "source_location": "L142"}, {"caller_nid": "utils_capital_filter_filter_stocks_by_capital", "callee": "warning", "source_file": "C:\\Users\\rshiv\\nse-trading-bot\\backend\\utils\\capital_filter.py", "source_location": "L145"}, {"caller_nid": "utils_capital_filter_filter_stocks_by_capital", "callee": "append", "source_file": "C:\\Users\\rshiv\\nse-trading-bot\\backend\\utils\\capital_filter.py", "source_location": "L146"}, {"caller_nid": "utils_capital_filter_filter_stocks_by_capital", "callee": "sleep", "source_file": "C:\\Users\\rshiv\\nse-trading-bot\\backend\\utils\\capital_filter.py", "source_location": "L147"}, {"caller_nid": "utils_capital_filter_filter_stocks_by_capital", "callee": "info", "source_file": "C:\\Users\\rshiv\\nse-trading-bot\\backend\\utils\\capital_filter.py", "source_location": "L151"}, {"caller_nid": "utils_capital_filter_filter_stocks_by_capital", "callee": "len", "source_file": "C:\\Users\\rshiv\\nse-trading-bot\\backend\\utils\\capital_filter.py", "source_location": "L152"}, {"caller_nid": "utils_capital_filter_filter_stocks_by_capital", "callee": "len", "source_file": "C:\\Users\\rshiv\\nse-trading-bot\\backend\\utils\\capital_filter.py", "source_location": "L153"}, {"caller_nid": "utils_capital_filter_filter_stocks_by_capital", "callee": "info", "source_file": "C:\\Users\\rshiv\\nse-trading-bot\\backend\\utils\\capital_filter.py", "source_location": "L156"}, {"caller_nid": "utils_capital_filter_filter_stocks_by_capital", "callee": "len", "source_file": "C:\\Users\\rshiv\\nse-trading-bot\\backend\\utils\\capital_filter.py", "source_location": "L157"}, {"caller_nid": "utils_capital_filter_filter_stocks_by_capital", "callee": "len", "source_file": "C:\\Users\\rshiv\\nse-trading-bot\\backend\\utils\\capital_filter.py", "source_location": "L158"}, {"caller_nid": "utils_capital_filter_filter_stocks_by_capital", "callee": "len", "source_file": "C:\\Users\\rshiv\\nse-trading-bot\\backend\\utils\\capital_filter.py", "source_location": "L158"}, {"caller_nid": "utils_capital_filter_filter_stocks_by_capital", "callee": "info", "source_file": "C:\\Users\\rshiv\\nse-trading-bot\\backend\\utils\\capital_filter.py", "source_location": "L165"}, {"caller_nid": "utils_capital_filter_filter_stocks_by_capital", "callee": "len", "source_file": "C:\\Users\\rshiv\\nse-trading-bot\\backend\\utils\\capital_filter.py", "source_location": "L166"}, {"caller_nid": "utils_capital_filter_filter_stocks_by_capital", "callee": "info", "source_file": "C:\\Users\\rshiv\\nse-trading-bot\\backend\\utils\\capital_filter.py", "source_location": "L167"}, {"caller_nid": "utils_capital_filter_filter_stocks_by_capital", "callee": "len", "source_file": "C:\\Users\\rshiv\\nse-trading-bot\\backend\\utils\\capital_filter.py", "source_location": "L167"}]}